Metadata-Version: 2.1
Name: OpencvPyqt6
Version: 0.0.1
Summary: This package is for accelerate process creating PYQT6 application
Author: aji-ptn
License-File: LICENSE
